{"Lat":0,"Long":0,"Date":"2021-06-09T08:33:29-04:00","Orientation":1,"Exif":{"ApertureValue":2.2000000003969706,"BrightnessValue|*imagemeta.rat[int32]":"-10452/14353","ComponentsConfiguration":"1 2 3 0","CompositeImage|uint16":"2","CreateDate":"2021:06:09 08:33:29","CustomRendered|uint16":"8","DateTimeOriginal":"2021:06:09 08:33:29","ExposureCompensation|*imagemeta.rat[int32]":"0","ExposureTime|*imagemeta.rat[uint32]":"1/15","FNumber|*imagemeta.rat[uint32]":"11/5","FocalLengthIn35mmFormat|uint16":"64","FocalLength|*imagemeta.rat[uint32]":"15/2","HostComputer":"iPhone 12 Pro Max","ISO|uint16":"500","LensInfo":"5.1 7.5 1.6 2.2","LensMake":"Apple","LensModel":"iPhone 12 Pro Max back dual camera 7.5mm f/2.2","Make":"Apple","MakerNoteApple":"Apple iOSMM)hïŋ―ïŋ―hïŋ―ïŋ―`ïŋ―ïŋ― %ïŋ―!ïŋ―#ïŋ―%ïŋ―\u0026'ïŋ―(+%ïŋ―-ïŋ―./_3456)78z9:;\u003c=*Yïŋ―JC \u003c0\u003e5N9AA\u0026 6?\u003eaj;A*Rïŋ―T$Xïŋ―7=/Pïŋ―nïŋ―P]ïŋ―=A2!'w|ïŋ―ïŋ―ïŋ―QFD62hïŋ―ïŋ―ïŋ―fïŋ―ïŋ―lS[FG8$mïŋ―5haïŋ―ïŋ―ïŋ―41:E;)ïŋ―rïŋ―Ntjïŋ―6#,C\u003e-\u003eïŋ―\\ïŋ―ïŋ―wïŋ―ïŋ―:(=E3ïŋ―ïŋ―Eïŋ―ïŋ―]3: =F7 ïŋ―ïŋ―Y pïŋ―ïŋ―ïŋ―ïŋ―ïŋ―ïŋ―u@A8*eïŋ―gïŋ―ïŋ―ïŋ―`/gïŋ―FG\u003c1:\"?6ïŋ―ïŋ―ïŋ―ïŋ―ïŋ―ïŋ―ïŋ―XKK@6ïŋ―ïŋ―ïŋ―ïŋ―Yïŋ―ïŋ―ïŋ―ïŋ―OQHBR,jïŋ―ïŋ―ïŋ―ïŋ―ïŋ―ïŋ―ïŋ―UPSVU$aENuVVTabmsbplist00ïŋ―UflagsUvalueYtimescaleUepochïŋ―ïŋ―ïŋ―ïŋ―;ïŋ―ïŋ―'-/8=?ïŋ―ïŋ―sïŋ―ïŋ―ïŋ―ïŋ―}ïŋ―ïŋ―ïŋ―ïŋ―ïŋ―ïŋ―-ïŋ―#ïŋ―RBq825s\"ïŋ―3F1E9906-C261-4FA2-976E-CA69A7C11DEFïŋ―Pïŋ―*3EAAAE053-EE3C-406B-9F2F-F32FBE0720F3","Model":"iPhone 12 Pro Max","ModifyDate":"2021:06:09 08:33:29","OffsetTime":"-04:00","OffsetTimeDigitized":"-04:00","OffsetTimeOriginal":"-04:00","Orientation|uint16":"1","SceneCaptureType|uint16":"0","SceneType|uint8":"1","ShutterSpeedValue":0.06666900026532065,"Software":"14.6","SubSecTimeDigitized|int":"804","SubSecTimeOriginal|int":"804","SubSecTime|int":"804","SubjectArea":"2003 1502 2128 1342","TileLength|uint32":"512","TileWidth|uint32":"512","YCbCrPositioning|uint16":"1"},"IPTC":{},"XMP":{}}
