{"Lat":0,"Long":0,"Date":"2021-11-17T07:33:06-05:00","Orientation":1,"Exif":{"ApertureValue":1.5999999994623026,"BrightnessValue|*imagemeta.rat[int32]":"-10106/20835","ComponentsConfiguration":"1 2 3 0","CompositeImage|uint16":"2","CreateDate":"2021:11:17 07:33:06","DateTimeOriginal":"2021:11:17 07:33:06","ExposureCompensation|*imagemeta.rat[int32]":"0","ExposureTime|*imagemeta.rat[uint32]":"1/30","FNumber|*imagemeta.rat[uint32]":"8/5","FocalLengthIn35mmFormat|uint16":"26","FocalLength|*imagemeta.rat[uint32]":"51/10","HostComputer":"iPhone 12 Pro Max","ISO|uint16":"500","LensInfo":"1.5399999618512084 7.5 1.6 2.4","LensMake":"Apple","LensModel":"iPhone 12 Pro Max back triple camera 5.1mm f/1.6","Make":"Apple","MakerNoteApple":"Apple iOSMM*hïŋ―ïŋ―tïŋ―!ïŋ― ïŋ― %ïŋ―!ïŋ―#ïŋ―%ïŋ―\u0026'ïŋ―+%ïŋ―-ïŋ―./m030456578!9:;\u003c=ABJ%;ïŋ―+E`Bïŋ―! !ïŋ―'Lïŋ―ïŋ―3R%R0ïŋ―ïŋ―ïŋ―ïŋ―ïŋ―oïŋ―ïŋ―ïŋ―H'$7a~ïŋ―fïŋ―\\tb=5ïŋ―ïŋ―{ïŋ―?sq_:\"\u003c}Jïŋ―ïŋ―.aTXMZ@+tBUSHG/ïŋ―ïŋ―ïŋ―ïŋ―_Xïŋ―ïŋ―XN,Fïŋ―ïŋ―ïŋ―e]ïŋ―ïŋ―ïŋ―ïŋ―HAB\u003cMïŋ―ïŋ―ïŋ―%ïŋ―ïŋ―ïŋ― \u003cA31hïŋ―ïŋ―ïŋ―~q*!e%%ïŋ―Eifïŋ―ïŋ―ïŋ―ïŋ―\"Lïŋ―ïŋ―!-eïŋ―ïŋ―ïŋ― #\" ïŋ―\"5ïŋ―ïŋ―ïŋ―\u0026#$ïŋ―\u0026=ïŋ―ïŋ―ïŋ―bplist00ïŋ―UflagsUvalueYtimescaleUepochïŋ―ïŋ―)4D];ïŋ―ïŋ―'-/8=?ïŋ―ïŋ―ïŋ―R59ïŋ―ïŋ―ïŋ―Óïŋ―ïŋ―Ümc%?BP q750n5421FA71-885D-4146-B631-27AE50B17C9Cïŋ―A'ïŋ―\"ïŋ―ïŋ―ïŋ―'AC17C6241-1F09-42FD-B010-B291592DA8E4","Model":"iPhone 12 Pro Max","ModifyDate":"2021:11:17 07:33:06","OffsetTime":"-05:00","OffsetTimeDigitized":"-05:00","OffsetTimeOriginal":"-05:00","Orientation|uint16":"1","SceneCaptureType|uint16":"0","SceneType|uint8":"1","ShutterSpeedValue":0.03333300005442942,"Software":"15.0.2","SubSecTimeDigitized|int":"905","SubSecTimeOriginal|int":"905","SubSecTime|int":"905","SubjectArea":"2015 1509 2323 1327","TileLength|uint32":"512","TileWidth|uint32":"512","YCbCrPositioning|uint16":"1"},"IPTC":{},"XMP":{}}
